pyakta-0.5.0.dist-info/METADATA
pyakta-0.5.0.dist-info/WHEEL
pyakta-0.5.0.dist-info/entry_points.txt
pyakta-0.5.0.dist-info/licenses/LICENSE
pyakta/__init__.py
pyakta/credentials.py
pyakta/did.py
pyakta/models.py
pyakta-0.5.0.dist-info/RECORD
