Metadata-Version: 2.1
Name: pyakta
Version: 0.5.0
Summary: A Python library for Akta Agent to Agent Trust Protocol
Author-Email: Luke Hinds <lukehinds@gmail.com>
License: Apache License 2.0
Classifier: Development Status :: 3 - Alpha
Classifier: Intended Audience :: Developers
Classifier: License :: OSI Approved :: Apache Software License
Classifier: Programming Language :: Python :: 3
Project-URL: Homepage, https://github.com/lukehinds/pyakta
Project-URL: Repository, https://github.com/lukehinds/pyakta
Requires-Python: >=3.11
Requires-Dist: base58>=2.1.1
Requires-Dist: pynacl>=1.5.0
Requires-Dist: pydantic>=2.11.0
Requires-Dist: pyld>=2.0.4
Requires-Dist: requests>=2.32.3
Requires-Dist: httpx>=0.28.1
Provides-Extra: dev
Requires-Dist: pytest>=8.3.4; extra == "dev"
Requires-Dist: pytest-cov>=6.0.0; extra == "dev"
Requires-Dist: ruff~=0.9; extra == "dev"
Requires-Dist: bandit>=1.8.3; extra == "dev"
